odoo10_addon_l10n_es_mis_report-10.0.2.1.1-py2.7-nspkg.pth
odoo/addons/l10n_es_mis_report/README.rst
odoo/addons/l10n_es_mis_report/__init__.py
odoo/addons/l10n_es_mis_report/__manifest__.py
odoo/addons/l10n_es_mis_report/data/mis_report_balance_abreviated.xml
odoo/addons/l10n_es_mis_report/data/mis_report_balance_normal.xml
odoo/addons/l10n_es_mis_report/data/mis_report_balance_sme.xml
odoo/addons/l10n_es_mis_report/data/mis_report_pyg_abreviated.xml
odoo/addons/l10n_es_mis_report/data/mis_report_pyg_normal.xml
odoo/addons/l10n_es_mis_report/data/mis_report_pyg_sme.xml
odoo/addons/l10n_es_mis_report/data/mis_report_revenues_expenses_normal.xml
odoo/addons/l10n_es_mis_report/data/mis_report_styles.xml
odoo/addons/l10n_es_mis_report/migrations/10.0.2.0.0/pre-migration.py
odoo10_addon_l10n_es_mis_report-10.0.2.1.1.dist-info/DESCRIPTION.rst
odoo10_addon_l10n_es_mis_report-10.0.2.1.1.dist-info/METADATA
odoo10_addon_l10n_es_mis_report-10.0.2.1.1.dist-info/RECORD
odoo10_addon_l10n_es_mis_report-10.0.2.1.1.dist-info/WHEEL
odoo10_addon_l10n_es_mis_report-10.0.2.1.1.dist-info/metadata.json
odoo10_addon_l10n_es_mis_report-10.0.2.1.1.dist-info/namespace_packages.txt
odoo10_addon_l10n_es_mis_report-10.0.2.1.1.dist-info/top_level.txt
